Metadata-Version: 2.1
Name: langroid-pydantic-v1
Version: 0.1.0
Summary: Dummy pkg to depend on Pydantic v1, for use with Langroid
Author: Prasad Chalasani
Author-email: pchalasani@gmail.com
Requires-Python: >=3.10,<4.0
Classifier: Programming Language :: Python :: 3
Classifier: Programming Language :: Python :: 3.10
Classifier: Programming Language :: Python :: 3.11
Classifier: Programming Language :: Python :: 3.12
Requires-Dist: pydantic (>=1.0,<2.0)
